midlearn/__init__.py
midlearn/_r_interface.py
midlearn/api.py
midlearn/exceptions.py
midlearn/plotting.py
midlearn/plotting_theme.py
midlearn/utils.py
midlearn-0.1.3.dist-info/licenses/LICENSE.md
midlearn-0.1.3.dist-info/METADATA
midlearn-0.1.3.dist-info/WHEEL
midlearn-0.1.3.dist-info/top_level.txt
midlearn-0.1.3.dist-info/RECORD
