Metadata-Version: 2.4
Name: midlearn
Version: 0.1.3
Summary: Python Wrapper of the 'midr' R package to interpret black-box models.
Author-email: Ryoichi Asashiba <ryoichi.asashiba@gmail.com>
Project-URL: Issues, https://github.com/ryo-asashi/midlearn/issues
Classifier: Programming Language :: Python :: 3
Classifier: License :: OSI Approved :: MIT License
Classifier: Operating System :: OS Independent
Requires-Python: >=3.8
License-File: LICENSE.md
Requires-Dist: numpy
Requires-Dist: pandas
Requires-Dist: scikit-learn
Requires-Dist: rpy2>=3.5.0
Requires-Dist: plotnine
Requires-Dist: mizani
Dynamic: license-file
